Metadata-Version: 1.0
Name: kostyaos
Version: 1.0
Summary: Kostya OS on Python
Home-page: UNKNOWN
Author: UNKNOWN
Author-email: admin@kostya-os.ru
License: UNKNOWN
Platform: UNKNOWN
